genomicarrays/GenomicArrayDataset.py
genomicarrays/GenomicArrayDatasetSlice.py
genomicarrays/__init__.py
genomicarrays/build_genomicarray.py
genomicarrays/build_options.py
genomicarrays/buildutils_tiledb_array.py
genomicarrays/dataloader.py
genomicarrays/queryutils_tiledb_frame.py
genomicarrays/utils_bw.py
GenomicArrays-0.2.2.dist-info/LICENSE.txt
GenomicArrays-0.2.2.dist-info/METADATA
GenomicArrays-0.2.2.dist-info/WHEEL
GenomicArrays-0.2.2.dist-info/top_level.txt
GenomicArrays-0.2.2.dist-info/RECORD
