Metadata-Version: 2.2
Name: GenomicArrays
Version: 0.2.2
Summary: Genomic region based arrays backed by TileDB
Home-page: https://github.com/biocpy/genomicarrays
Author: Jayaram Kancherla
Author-email: jayaram.kancherla@gmail.com
License: MIT
Project-URL: Documentation, https://github.com/biocpy/genomicarrays
Platform: any
Classifier: Development Status :: 4 - Beta
Classifier: Programming Language :: Python
Requires-Python: >=3.9
License-File: LICENSE.txt
Requires-Dist: importlib-metadata; python_version < "3.8"
Requires-Dist: cellarr
Requires-Dist: tiledb
Requires-Dist: pyBigWig
Requires-Dist: pandas
Requires-Dist: numpy
Requires-Dist: pyarrow>=1.0
Requires-Dist: mopsy
Requires-Dist: genomicranges
Requires-Dist: pyfaidx
Provides-Extra: optional
Requires-Dist: torch; extra == "optional"
Requires-Dist: pytorch-lightning; extra == "optional"
Provides-Extra: testing
Requires-Dist: setuptools; extra == "testing"
Requires-Dist: pytest; extra == "testing"
Requires-Dist: pytest-cov; extra == "testing"
